[
    {
        "id":  1,
        "beach_id":  1,
        "title":  "Bai Chay Adventure Tour",
        "image":  "/assets/image/1.jpg",
        "description":  "Explore the beautiful Bai Chay beach with guided tour",
        "duration_days":  1,
        "price":  61.41,
        "original_price":  80.18,
        "capacity":  40,
        "departure_dates":  [
                                "2025-11-17T08:00:00",
                                "2025-11-20T08:00:00",
                                "2025-11-23T08:00:00",
                                "2025-11-26T08:00:00"
                            ],
        "return_time":  "2025-12-12T08:00:00",
        "included_services":  [
                                  "Transportation",
                                  "Lunch",
                                  "Guide",
                                  "Equipment"
                              ],
        "excluded_services":  [
                                  "Personal expenses",
                                  "Tips"
                              ],
        "highlights":  [
                           "Golden sand beach",
                           "Water sports",
                           "Local seafood",
                           "Sunset viewing"
                       ],
        "status":  "confirmed",
        "created_at":  "2025-12-10 18:29:58",
        "updated_at":  "2025-11-14 18:35:10",
        "ceo_id":  2,
        "departure_time":  "2025-12-11T08:00:00"
    },
    {
        "id":  2,
        "beach_id":  1,
        "title":  "Bai Chay Sunset Tour",
        "image":  "/assets/image/1.jpg",
        "description":  "Enjoy the sunset at Bai Chay beach",
        "duration_days":  3,
        "price":  70,
        "original_price":  90,
        "capacity":  30,
        "departure_dates":  [
                                "2025-11-17T08:00:00",
                                "2025-11-21T08:00:00",
                                "2025-11-25T08:00:00",
                                "2025-11-29T08:00:00"
                            ],
        "return_time":  "2025-12-14T08:00:00",
        "included_services":  [
                                  "Transportation",
                                  "Dinner",
                                  "Guide",
                                  "Sunset viewing"
                              ],
        "excluded_services":  [
                                  "Personal expenses",
                                  "Tips"
                              ],
        "highlights":  [
                           "Sunset viewing",
                           "Romantic atmosphere",
                           "Local cuisine",
                           "Beach relaxation"
                       ],
        "status":  "confirmed",
        "created_at":  "2025-12-10 18:29:58",
        "updated_at":  "2025-11-14 18:35:10",
        "ceo_id":  2,
        "departure_time":  "2025-12-11T08:00:00"
    },
    {
        "id":  3,
        "beach_id":  2,
        "title":  "Do Son Cultural Tour",
        "image":  "/assets/image/2.jpg",
        "description":  "Discover the cultural heritage of Do Son beach",
        "duration_days":  1,
        "price":  40.32,
        "original_price":  82.2,
        "capacity":  40,
        "departure_dates":  [
                                "2025-11-17T08:00:00",
                                "2025-11-19T08:00:00",
                                "2025-11-22T08:00:00",
                                "2025-11-24T08:00:00"
                            ],
        "return_time":  "2025-12-12T08:00:00",
        "included_services":  [
                                  "Transportation",
                                  "Lunch",
                                  "Cultural guide",
                                  "Temple visits"
                              ],
        "excluded_services":  [
                                  "Personal expenses",
                                  "Tips"
                              ],
        "highlights":  [
                           "Historical temples",
                           "Local culture",
                           "Traditional food",
                           "Ocean walks"
                       ],
        "status":  "confirmed",
        "created_at":  "2025-12-10 18:29:58",
        "updated_at":  "2025-11-14 18:35:10",
        "ceo_id":  2,
        "departure_time":  "2025-12-11T08:00:00"
    },
    {
        "id":  4,
        "beach_id":  2,
        "title":  "Do Son Adventure Tour",
        "image":  "/assets/image/2.jpg",
        "description":  "Adventure activities at Do Son beach",
        "duration_days":  1,
        "price":  50,
        "original_price":  85,
        "capacity":  35,
        "departure_dates":  [
                                "2025-11-17T08:00:00",
                                "2025-11-19T08:00:00",
                                "2025-11-21T08:00:00",
                                "2025-11-23T08:00:00"
                            ],
        "return_time":  "2025-12-12T08:00:00",
        "included_services":  [
                                  "Transportation",
                                  "Lunch",
                                  "Adventure guide",
                                  "Water sports equipment"
                              ],
        "excluded_services":  [
                                  "Personal expenses",
                                  "Tips"
                              ],
        "highlights":  [
                           "Water sports",
                           "Beach activities",
                           "Adventure games",
                           "Team building"
                       ],
        "status":  "confirmed",
        "created_at":  "2025-12-10 18:29:58",
        "updated_at":  "2025-11-14 18:35:10",
        "ceo_id":  2,
        "departure_time":  "2025-12-11T08:00:00"
    },
    {
        "id":  5,
        "beach_id":  3,
        "title":  "An Bang Beach Discovery",
        "image":  "/assets/image/3.jpg",
        "description":  "Discover the beauty of An Bang Beach",
        "duration_days":  1,
        "price":  79.56,
        "original_price":  89.82,
        "capacity":  40,
        "departure_dates":  [
                                "2025-11-17T08:00:00",
                                "2025-11-20T08:00:00",
                                "2025-11-24T08:00:00",
                                "2025-11-27T08:00:00"
                            ],
        "return_time":  "2025-12-12T08:00:00",
        "included_services":  [
                                  "Transportation",
                                  "Lunch",
                                  "Guide",
                                  "Beach equipment"
                              ],
        "excluded_services":  [
                                  "Personal expenses",
                                  "Tips"
                              ],
        "highlights":  [
                           "Golden sand beach",
                           "Clear waters",
                           "Local cuisine",
                           "Relaxation"
                       ],
        "status":  "confirmed",
        "created_at":  "2025-12-10 18:29:58",
        "updated_at":  "2025-11-14 18:35:10",
        "ceo_id":  2,
        "departure_time":  "2025-12-11T08:00:00"
    },
    {
        "id":  6,
        "beach_id":  3,
        "title":  "An Bang Sunset Experience",
        "image":  "/assets/image/3.jpg",
        "description":  "Experience the magical sunset at An Bang",
        "duration_days":  1,
        "price":  85,
        "original_price":  95,
        "capacity":  30,
        "departure_dates":  [
                                "2025-11-17T16:00:00",
                                "2025-11-19T16:00:00",
                                "2025-11-22T16:00:00",
                                "2025-11-25T16:00:00"
                            ],
        "return_time":  "2025-12-12T08:00:00",
        "included_services":  [
                                  "Transportation",
                                  "Dinner",
                                  "Guide",
                                  "Sunset viewing"
                              ],
        "excluded_services":  [
                                  "Personal expenses",
                                  "Tips"
                              ],
        "highlights":  [
                           "Sunset viewing",
                           "Romantic atmosphere",
                           "Local seafood",
                           "Beach relaxation"
                       ],
        "status":  "confirmed",
        "created_at":  "2025-12-10 18:29:58",
        "updated_at":  "2025-11-14 18:35:10",
        "ceo_id":  2,
        "departure_time":  "2025-12-11T08:00:00"
    },
    {
        "id":  7,
        "beach_id":  4,
        "title":  "Tuan Chau Nature Tour",
        "image":  "/assets/image/4.jpg",
        "description":  "Explore the natural beauty of Tuan Chau",
        "duration_days":  1,
        "price":  41.42,
        "original_price":  85.99,
        "capacity":  30,
        "departure_dates":  [
                                "2025-11-17T08:00:00",
                                "2025-11-21T08:00:00",
                                "2025-11-25T08:00:00",
                                "2025-11-29T08:00:00"
                            ],
        "return_time":  "2025-12-12T08:00:00",
        "included_services":  [
                                  "Transportation",
                                  "Lunch",
                                  "Nature guide",
                                  "Hiking equipment"
                              ],
        "excluded_services":  [
                                  "Personal expenses",
                                  "Tips"
                              ],
        "highlights":  [
                           "Natural beauty",
                           "Hiking trails",
                           "Wildlife viewing",
                           "Photography"
                       ],
        "status":  "confirmed",
        "created_at":  "2025-12-10 18:29:58",
        "updated_at":  "2025-11-14 18:35:10",
        "ceo_id":  2,
        "departure_time":  "2025-12-11T08:00:00"
    },
    {
        "id":  8,
        "beach_id":  4,
        "title":  "Tuan Chau Adventure",
        "image":  "/assets/image/4.jpg",
        "description":  "Adventure activities at Tuan Chau Beach",
        "duration_days":  1,
        "price":  55,
        "original_price":  90,
        "capacity":  25,
        "departure_dates":  [
                                "2025-11-17T08:00:00",
                                "2025-11-20T08:00:00",
                                "2025-11-23T08:00:00",
                                "2025-11-26T08:00:00"
                            ],
        "return_time":  "2025-12-12T08:00:00",
        "included_services":  [
                                  "Transportation",
                                  "Lunch",
                                  "Adventure guide",
                                  "Adventure equipment"
                              ],
        "excluded_services":  [
                                  "Personal expenses",
                                  "Tips"
                              ],
        "highlights":  [
                           "Adventure activities",
                           "Rock climbing",
                           "Water sports",
                           "Team building"
                       ],
        "status":  "confirmed",
        "created_at":  "2025-12-10 18:29:58",
        "updated_at":  "2025-11-14 18:35:10",
        "ceo_id":  2,
        "departure_time":  "2025-12-11T08:00:00"
    },
    {
        "id":  9,
        "beach_id":  5,
        "title":  "Lang Co Beach Retreat",
        "image":  "/assets/image/5.jpg",
        "description":  "Peaceful retreat at Lang Co Beach",
        "duration_days":  1,
        "price":  81.03,
        "original_price":  93.17,
        "capacity":  30,
        "departure_dates":  [
                                "2025-11-17T08:00:00",
                                "2025-11-20T08:00:00",
                                "2025-11-23T08:00:00",
                                "2025-11-26T08:00:00"
                            ],
        "return_time":  "2025-12-12T08:00:00",
        "included_services":  [
                                  "Transportation",
                                  "Lunch",
                                  "Guide",
                                  "Relaxation equipment"
                              ],
        "excluded_services":  [
                                  "Personal expenses",
                                  "Tips"
                              ],
        "highlights":  [
                           "Peaceful atmosphere",
                           "Relaxation",
                           "Local cuisine",
                           "Beach meditation"
                       ],
        "status":  "confirmed",
        "created_at":  "2025-12-10 18:29:58",
        "updated_at":  "2025-11-14 18:35:10",
        "ceo_id":  2,
        "departure_time":  "2025-12-11T08:00:00"
    },
    {
        "id":  10,
        "beach_id":  5,
        "title":  "Lang Co Cultural Experience",
        "image":  "/assets/image/5.jpg",
        "description":  "Cultural experience at Lang Co Beach",
        "duration_days":  1,
        "price":  90,
        "original_price":  100,
        "capacity":  25,
        "departure_dates":  [
                                "2025-11-17T08:00:00",
                                "2025-11-20T08:00:00",
                                "2025-11-23T08:00:00",
                                "2025-11-26T08:00:00"
                            ],
        "return_time":  "2025-12-12T08:00:00",
        "included_services":  [
                                  "Transportation",
                                  "Lunch",
                                  "Cultural guide",
                                  "Cultural activities"
                              ],
        "excluded_services":  [
                                  "Personal expenses",
                                  "Tips"
                              ],
        "highlights":  [
                           "Local culture",
                           "Traditional activities",
                           "Cultural workshops",
                           "Local interaction"
                       ],
        "status":  "confirmed",
        "created_at":  "2025-12-10 18:29:58",
        "updated_at":  "2025-11-14 18:35:10",
        "ceo_id":  2,
        "departure_time":  "2025-12-11T08:00:00"
    },
    {
        "id":  11,
        "beach_id":  6,
        "title":  "Quang Lang Beach Tour",
        "image":  "/assets/image/6.jpg",
        "description":  "Explore Quang Lang Beach",
        "duration_days":  1,
        "price":  62.24,
        "original_price":  82.06,
        "capacity":  40,
        "departure_dates":  [
                                "2025-11-17T08:00:00",
                                "2025-11-20T08:00:00",
                                "2025-11-23T08:00:00",
                                "2025-11-26T08:00:00"
                            ],
        "return_time":  "2025-12-12T08:00:00",
        "included_services":  [
                                  "Transportation",
                                  "Lunch",
                                  "Guide",
                                  "Beach equipment"
                              ],
        "excluded_services":  [
                                  "Personal expenses",
                                  "Tips"
                              ],
        "highlights":  [
                           "Golden sand beach",
                           "Clear waters",
                           "Local cuisine",
                           "Beach activities"
                       ],
        "status":  "confirmed",
        "created_at":  "2025-12-10 18:29:58",
        "updated_at":  "2025-11-14 18:35:10",
        "ceo_id":  2,
        "departure_time":  "2025-12-11T08:00:00"
    },
    {
        "id":  12,
        "beach_id":  6,
        "title":  "Quang Lang Sunset Tour",
        "image":  "/assets/image/6.jpg",
        "description":  "Sunset experience at Quang Lang",
        "duration_days":  1,
        "price":  70,
        "original_price":  85,
        "capacity":  35,
        "departure_dates":  [
                                "2025-11-17T08:00:00",
                                "2025-11-20T08:00:00",
                                "2025-11-23T08:00:00",
                                "2025-11-26T08:00:00"
                            ],
        "return_time":  "2025-12-12T08:00:00",
        "included_services":  [
                                  "Transportation",
                                  "Dinner",
                                  "Guide",
                                  "Sunset viewing"
                              ],
        "excluded_services":  [
                                  "Personal expenses",
                                  "Tips"
                              ],
        "highlights":  [
                           "Sunset viewing",
                           "Romantic atmosphere",
                           "Local seafood",
                           "Beach relaxation"
                       ],
        "status":  "confirmed",
        "created_at":  "2025-12-10 18:29:58",
        "updated_at":  "2025-11-14 18:35:10",
        "ceo_id":  2,
        "departure_time":  "2025-12-11T08:00:00"
    },
    {
        "id":  13,
        "beach_id":  7,
        "title":  "Dong Chau Beach Adventure",
        "image":  "/assets/image/7.jpg",
        "description":  "Adventure at Dong Chau Beach",
        "duration_days":  1,
        "price":  75.06,
        "original_price":  85.92,
        "capacity":  40,
        "departure_dates":  [
                                "2025-11-17T08:00:00",
                                "2025-11-20T08:00:00",
                                "2025-11-23T08:00:00",
                                "2025-11-26T08:00:00"
                            ],
        "return_time":  "2025-12-12T08:00:00",
        "included_services":  [
                                  "Transportation",
                                  "Lunch",
                                  "Adventure guide",
                                  "Adventure equipment"
                              ],
        "excluded_services":  [
                                  "Personal expenses",
                                  "Tips"
                              ],
        "highlights":  [
                           "Adventure activities",
                           "Water sports",
                           "Beach games",
                           "Team building"
                       ],
        "status":  "confirmed",
        "created_at":  "2025-12-10 18:29:58",
        "updated_at":  "2025-11-14 18:35:10",
        "ceo_id":  2,
        "departure_time":  "2025-12-11T08:00:00"
    },
    {
        "id":  14,
        "beach_id":  7,
        "title":  "Dong Chau Nature Walk",
        "image":  "/assets/image/7.jpg",
        "description":  "Nature walk at Dong Chau Beach",
        "duration_days":  1,
        "price":  80,
        "original_price":  90,
        "capacity":  30,
        "departure_dates":  [
                                "2025-11-17T08:00:00",
                                "2025-11-20T08:00:00",
                                "2025-11-23T08:00:00",
                                "2025-11-26T08:00:00"
                            ],
        "return_time":  "2025-12-12T08:00:00",
        "included_services":  [
                                  "Transportation",
                                  "Lunch",
                                  "Nature guide",
                                  "Hiking equipment"
                              ],
        "excluded_services":  [
                                  "Personal expenses",
                                  "Tips"
                              ],
        "highlights":  [
                           "Nature trails",
                           "Wildlife viewing",
                           "Photography",
                           "Peaceful atmosphere"
                       ],
        "status":  "confirmed",
        "created_at":  "2025-12-10 18:29:58",
        "updated_at":  "2025-11-14 18:35:10",
        "ceo_id":  2,
        "departure_time":  "2025-12-11T08:00:00"
    },
    {
        "id":  15,
        "beach_id":  8,
        "title":  "Hai Hoa Beach Experience",
        "image":  "/assets/image/8.jpg",
        "description":  "Experience Hai Hoa Beach",
        "duration_days":  1,
        "price":  49.96,
        "original_price":  98.94,
        "capacity":  50,
        "departure_dates":  [
                                "2025-11-17T08:00:00",
                                "2025-11-20T08:00:00",
                                "2025-11-23T08:00:00",
                                "2025-11-26T08:00:00"
                            ],
        "return_time":  "2025-12-12T08:00:00",
        "included_services":  [
                                  "Transportation",
                                  "Lunch",
                                  "Guide",
                                  "Beach equipment"
                              ],
        "excluded_services":  [
                                  "Personal expenses",
                                  "Tips"
                              ],
        "highlights":  [
                           "Vibrant atmosphere",
                           "Beach activities",
                           "Local culture",
                           "Entertainment"
                       ],
        "status":  "confirmed",
        "created_at":  "2025-12-10 18:29:58",
        "updated_at":  "2025-11-14 18:35:10",
        "ceo_id":  2,
        "departure_time":  "2025-12-11T08:00:00"
    },
    {
        "id":  16,
        "beach_id":  8,
        "title":  "Hai Hoa Water Sports",
        "image":  "/assets/image/8.jpg",
        "description":  "Water sports at Hai Hoa Beach",
        "duration_days":  1,
        "price":  60,
        "original_price":  100,
        "capacity":  40,
        "departure_dates":  [
                                "2025-11-17T08:00:00",
                                "2025-11-20T08:00:00",
                                "2025-11-23T08:00:00",
                                "2025-11-26T08:00:00"
                            ],
        "return_time":  "2025-12-12T08:00:00",
        "included_services":  [
                                  "Transportation",
                                  "Lunch",
                                  "Water sports guide",
                                  "Water sports equipment"
                              ],
        "excluded_services":  [
                                  "Personal expenses",
                                  "Tips"
                              ],
        "highlights":  [
                           "Water sports",
                           "Jet skiing",
                           "Parasailing",
                           "Beach volleyball"
                       ],
        "status":  "confirmed",
        "created_at":  "2025-12-10 18:29:58",
        "updated_at":  "2025-11-14 18:35:10",
        "ceo_id":  2,
        "departure_time":  "2025-12-11T08:00:00"
    },
    {
        "id":  17,
        "beach_id":  9,
        "title":  "Sam Son Beach Tour",
        "image":  "/assets/image/9.jpg",
        "description":  "Tour Sam Son Beach",
        "duration_days":  1,
        "price":  50.17,
        "original_price":  98.5,
        "capacity":  50,
        "departure_dates":  [
                                "2025-11-17T08:00:00",
                                "2025-11-20T08:00:00",
                                "2025-11-23T08:00:00",
                                "2025-11-26T08:00:00"
                            ],
        "return_time":  "2025-12-12T08:00:00",
        "included_services":  [
                                  "Transportation",
                                  "Lunch",
                                  "Guide",
                                  "Beach equipment"
                              ],
        "excluded_services":  [
                                  "Personal expenses",
                                  "Tips"
                              ],
        "highlights":  [
                           "Peaceful atmosphere",
                           "Beach relaxation",
                           "Local cuisine",
                           "Family activities"
                       ],
        "status":  "confirmed",
        "created_at":  "2025-12-10 18:29:58",
        "updated_at":  "2025-11-14 18:35:10",
        "ceo_id":  2,
        "departure_time":  "2025-12-11T08:00:00"
    },
    {
        "id":  18,
        "beach_id":  9,
        "title":  "Sam Son Cultural Tour",
        "image":  "/assets/image/9.jpg",
        "description":  "Cultural tour at Sam Son Beach",
        "duration_days":  1,
        "price":  65,
        "original_price":  100,
        "capacity":  40,
        "departure_dates":  [
                                "2025-11-17T08:00:00",
                                "2025-11-20T08:00:00",
                                "2025-11-23T08:00:00",
                                "2025-11-26T08:00:00"
                            ],
        "return_time":  "2025-12-12T08:00:00",
        "included_services":  [
                                  "Transportation",
                                  "Lunch",
                                  "Cultural guide",
                                  "Cultural activities"
                              ],
        "excluded_services":  [
                                  "Personal expenses",
                                  "Tips"
                              ],
        "highlights":  [
                           "Local culture",
                           "Traditional activities",
                           "Cultural workshops",
                           "Local interaction"
                       ],
        "status":  "confirmed",
        "created_at":  "2025-12-10 18:29:58",
        "updated_at":  "2025-11-14 18:35:10",
        "ceo_id":  2,
        "departure_time":  "2025-12-11T08:00:00"
    },
    {
        "id":  19,
        "beach_id":  10,
        "title":  "Bai Tam Tien Sa Discovery",
        "image":  "/assets/image/10.jpg",
        "description":  "Discover Bai Tam Tien Sa",
        "duration_days":  1,
        "price":  55.06,
        "original_price":  86.93,
        "capacity":  30,
        "departure_dates":  [
                                "2025-11-17T08:00:00",
                                "2025-11-20T08:00:00",
                                "2025-11-23T08:00:00",
                                "2025-11-26T08:00:00"
                            ],
        "return_time":  "2025-12-12T08:00:00",
        "included_services":  [
                                  "Transportation",
                                  "Lunch",
                                  "Guide",
                                  "Beach equipment"
                              ],
        "excluded_services":  [
                                  "Personal expenses",
                                  "Tips"
                              ],
        "highlights":  [
                           "Natural beauty",
                           "Clear waters",
                           "Local cuisine",
                           "Beach exploration"
                       ],
        "status":  "confirmed",
        "created_at":  "2025-12-10 18:29:58",
        "updated_at":  "2025-11-14 18:35:10",
        "ceo_id":  2,
        "departure_time":  "2025-12-11T08:00:00"
    },
    {
        "id":  20,
        "beach_id":  10,
        "title":  "Bai Tam Tien Sa Adventure",
        "image":  "/assets/image/10.jpg",
        "description":  "Adventure at Bai Tam Tien Sa",
        "duration_days":  1,
        "price":  70,
        "original_price":  90,
        "capacity":  25,
        "departure_dates":  [
                                "2025-11-17T08:00:00",
                                "2025-11-20T08:00:00",
                                "2025-11-23T08:00:00",
                                "2025-11-26T08:00:00"
                            ],
        "return_time":  "2025-12-12T08:00:00",
        "included_services":  [
                                  "Transportation",
                                  "Lunch",
                                  "Adventure guide",
                                  "Adventure equipment"
                              ],
        "excluded_services":  [
                                  "Personal expenses",
                                  "Tips"
                              ],
        "highlights":  [
                           "Adventure activities",
                           "Rock climbing",
                           "Water sports",
                           "Exploration"
                       ],
        "status":  "confirmed",
        "created_at":  "2025-12-10 18:29:58",
        "updated_at":  "2025-11-14 18:35:10",
        "ceo_id":  2,
        "departure_time":  "2025-12-11T08:00:00"
    },
    {
        "id":  21,
        "beach_id":  11,
        "title":  "My Khe Beach Experience",
        "image":  "/assets/image/11.jpg",
        "description":  "Experience My Khe Beach",
        "duration_days":  1,
        "price":  80.19,
        "original_price":  92.88,
        "capacity":  30,
        "departure_dates":  [
                                "2025-11-17T08:00:00",
                                "2025-11-20T08:00:00",
                                "2025-11-23T08:00:00",
                                "2025-11-26T08:00:00"
                            ],
        "return_time":  "2025-12-12T08:00:00",
        "included_services":  [
                                  "Transportation",
                                  "Lunch",
                                  "Guide",
                                  "Beach equipment"
                              ],
        "excluded_services":  [
                                  "Personal expenses",
                                  "Tips"
                              ],
        "highlights":  [
                           "Vibrant atmosphere",
                           "Beach activities",
                           "Local cuisine",
                           "Entertainment"
                       ],
        "status":  "confirmed",
        "created_at":  "2025-12-10 18:29:58",
        "updated_at":  "2025-11-14 18:35:10",
        "ceo_id":  2,
        "departure_time":  "2025-12-11T08:00:00"
    },
    {
        "id":  22,
        "beach_id":  11,
        "title":  "My Khe Sunset Tour",
        "image":  "/assets/image/11.jpg",
        "description":  "Sunset tour at My Khe Beach",
        "duration_days":  1,
        "price":  90,
        "original_price":  100,
        "capacity":  25,
        "departure_dates":  [
                                "2025-11-17T08:00:00",
                                "2025-11-20T08:00:00",
                                "2025-11-23T08:00:00",
                                "2025-11-26T08:00:00"
                            ],
        "return_time":  "2025-12-12T08:00:00",
        "included_services":  [
                                  "Transportation",
                                  "Dinner",
                                  "Guide",
                                  "Sunset viewing"
                              ],
        "excluded_services":  [
                                  "Personal expenses",
                                  "Tips"
                              ],
        "highlights":  [
                           "Sunset viewing",
                           "Romantic atmosphere",
                           "Local seafood",
                           "Beach relaxation"
                       ],
        "status":  "confirmed",
        "created_at":  "2025-12-10 18:29:58",
        "updated_at":  "2025-11-14 18:35:10",
        "ceo_id":  2,
        "departure_time":  "2025-12-11T08:00:00"
    },
    {
        "id":  23,
        "beach_id":  12,
        "title":  "Do Son Heritage Tour",
        "image":  "/assets/image/12.jpg",
        "description":  "Heritage tour at Do Son Beach",
        "duration_days":  1,
        "price":  40.32,
        "original_price":  82.2,
        "capacity":  40,
        "departure_dates":  [
                                "2025-11-17T08:00:00",
                                "2025-11-20T08:00:00",
                                "2025-11-23T08:00:00",
                                "2025-11-26T08:00:00"
                            ],
        "return_time":  "2025-12-12T08:00:00",
        "included_services":  [
                                  "Transportation",
                                  "Lunch",
                                  "Cultural guide",
                                  "Heritage sites"
                              ],
        "excluded_services":  [
                                  "Personal expenses",
                                  "Tips"
                              ],
        "highlights":  [
                           "Historical sites",
                           "Local culture",
                           "Traditional food",
                           "Heritage exploration"
                       ],
        "status":  "confirmed",
        "created_at":  "2025-12-10 18:29:58",
        "updated_at":  "2025-11-14 18:35:10",
        "ceo_id":  2,
        "departure_time":  "2025-12-11T08:00:00"
    },
    {
        "id":  24,
        "beach_id":  12,
        "title":  "Do Son Beach Adventure",
        "image":  "/assets/image/12.jpg",
        "description":  "Adventure at Do Son Beach",
        "duration_days":  1,
        "price":  55,
        "original_price":  85,
        "capacity":  35,
        "departure_dates":  [
                                "2025-11-17T08:00:00",
                                "2025-11-20T08:00:00",
                                "2025-11-23T08:00:00",
                                "2025-11-26T08:00:00"
                            ],
        "return_time":  "2025-12-12T08:00:00",
        "included_services":  [
                                  "Transportation",
                                  "Lunch",
                                  "Adventure guide",
                                  "Adventure equipment"
                              ],
        "excluded_services":  [
                                  "Personal expenses",
                                  "Tips"
                              ],
        "highlights":  [
                           "Adventure activities",
                           "Water sports",
                           "Beach games",
                           "Team building"
                       ],
        "status":  "confirmed",
        "created_at":  "2025-12-10 18:29:58",
        "updated_at":  "2025-11-14 18:35:10",
        "ceo_id":  2,
        "departure_time":  "2025-12-11T08:00:00"
    },
    {
        "id":  25,
        "beach_id":  13,
        "title":  "Cua Dai Beach Discovery",
        "image":  "/assets/image/13.jpg",
        "description":  "Discover Cua Dai Beach",
        "duration_days":  1,
        "price":  51.14,
        "original_price":  88.34,
        "capacity":  30,
        "departure_dates":  [
                                "2025-11-17T08:00:00",
                                "2025-11-20T08:00:00",
                                "2025-11-23T08:00:00",
                                "2025-11-26T08:00:00"
                            ],
        "return_time":  "2025-12-12T08:00:00",
        "included_services":  [
                                  "Transportation",
                                  "Lunch",
                                  "Guide",
                                  "Beach equipment"
                              ],
        "excluded_services":  [
                                  "Personal expenses",
                                  "Tips"
                              ],
        "highlights":  [
                           "Natural beauty",
                           "Clear waters",
                           "Local cuisine",
                           "Beach exploration"
                       ],
        "status":  "confirmed",
        "created_at":  "2025-12-10 18:29:58",
        "updated_at":  "2025-11-14 18:35:10",
        "ceo_id":  2,
        "departure_time":  "2025-12-11T08:00:00"
    },
    {
        "id":  26,
        "beach_id":  13,
        "title":  "Cua Dai Nature Tour",
        "image":  "/assets/image/13.jpg",
        "description":  "Nature tour at Cua Dai Beach",
        "duration_days":  1,
        "price":  65,
        "original_price":  90,
        "capacity":  25,
        "departure_dates":  [
                                "2025-11-17T08:00:00",
                                "2025-11-20T08:00:00",
                                "2025-11-23T08:00:00",
                                "2025-11-26T08:00:00"
                            ],
        "return_time":  "2025-12-12T08:00:00",
        "included_services":  [
                                  "Transportation",
                                  "Lunch",
                                  "Nature guide",
                                  "Hiking equipment"
                              ],
        "excluded_services":  [
                                  "Personal expenses",
                                  "Tips"
                              ],
        "highlights":  [
                           "Nature trails",
                           "Wildlife viewing",
                           "Photography",
                           "Peaceful atmosphere"
                       ],
        "status":  "confirmed",
        "created_at":  "2025-12-10 18:29:58",
        "updated_at":  "2025-11-14 18:35:10",
        "ceo_id":  2,
        "departure_time":  "2025-12-11T08:00:00"
    },
    {
        "id":  27,
        "beach_id":  14,
        "title":  "Co To Island Adventure",
        "image":  "/assets/image/14.jpg",
        "description":  "Adventure on Co To Island",
        "duration_days":  1,
        "price":  43.43,
        "original_price":  83.91,
        "capacity":  50,
        "departure_dates":  [
                                "2025-11-17T08:00:00",
                                "2025-11-20T08:00:00",
                                "2025-11-23T08:00:00",
                                "2025-11-26T08:00:00"
                            ],
        "return_time":  "2025-12-12T08:00:00",
        "included_services":  [
                                  "Transportation",
                                  "Lunch",
                                  "Adventure guide",
                                  "Adventure equipment"
                              ],
        "excluded_services":  [
                                  "Personal expenses",
                                  "Tips"
                              ],
        "highlights":  [
                           "Island adventure",
                           "Water sports",
                           "Beach activities",
                           "Exploration"
                       ],
        "status":  "confirmed",
        "created_at":  "2025-12-10 18:29:58",
        "updated_at":  "2025-11-14 18:35:10",
        "ceo_id":  2,
        "departure_time":  "2025-12-11T08:00:00"
    },
    {
        "id":  28,
        "beach_id":  14,
        "title":  "Co To Island Discovery",
        "image":  "/assets/image/14.jpg",
        "description":  "Discover Co To Island",
        "duration_days":  1,
        "price":  60,
        "original_price":  85,
        "capacity":  40,
        "departure_dates":  [
                                "2025-11-17T08:00:00",
                                "2025-11-20T08:00:00",
                                "2025-11-23T08:00:00",
                                "2025-11-26T08:00:00"
                            ],
        "return_time":  "2025-12-12T08:00:00",
        "included_services":  [
                                  "Transportation",
                                  "Lunch",
                                  "Guide",
                                  "Beach equipment"
                              ],
        "excluded_services":  [
                                  "Personal expenses",
                                  "Tips"
                              ],
        "highlights":  [
                           "Island beauty",
                           "Clear waters",
                           "Local cuisine",
                           "Beach relaxation"
                       ],
        "status":  "confirmed",
        "created_at":  "2025-12-10 18:29:58",
        "updated_at":  "2025-11-14 18:35:10",
        "ceo_id":  2,
        "departure_time":  "2025-12-11T08:00:00"
    },
    {
        "id":  29,
        "beach_id":  15,
        "title":  "Quy Hoa Beach Experience",
        "image":  "/assets/image/15.jpg",
        "description":  "Experience Quy Hoa Beach",
        "duration_days":  1,
        "price":  73.13,
        "original_price":  89.53,
        "capacity":  40,
        "departure_dates":  [
                                "2025-11-17T08:00:00",
                                "2025-11-20T08:00:00",
                                "2025-11-23T08:00:00",
                                "2025-11-26T08:00:00"
                            ],
        "return_time":  "2025-12-12T08:00:00",
        "included_services":  [
                                  "Transportation",
                                  "Lunch",
                                  "Guide",
                                  "Beach equipment"
                              ],
        "excluded_services":  [
                                  "Personal expenses",
                                  "Tips"
                              ],
        "highlights":  [
                           "Peaceful atmosphere",
                           "Beach relaxation",
                           "Local cuisine",
                           "Family activities"
                       ],
        "status":  "confirmed",
        "created_at":  "2025-12-10 18:29:58",
        "updated_at":  "2025-11-14 18:35:10",
        "ceo_id":  2,
        "departure_time":  "2025-12-11T08:00:00"
    },
    {
        "id":  30,
        "beach_id":  15,
        "title":  "Quy Hoa Sunset Tour",
        "image":  "/assets/image/15.jpg",
        "description":  "Sunset tour at Quy Hoa Beach",
        "duration_days":  22,
        "price":  80,
        "original_price":  95,
        "capacity":  35,
        "departure_dates":  [
                                "2025-11-17T08:00:00",
                                "2025-11-20T08:00:00",
                                "2025-11-23T08:00:00",
                                "2025-11-26T08:00:00"
                            ],
        "return_time":  "2026-01-02T08:00:00",
        "included_services":  [
                                  "Transportation",
                                  "Dinner",
                                  "Guide",
                                  "Sunset viewing"
                              ],
        "excluded_services":  [
                                  "Personal expenses",
                                  "Tips"
                              ],
        "highlights":  [
                           "Sunset viewing",
                           "Romantic atmosphere",
                           "Local seafood",
                           "Beach relaxation"
                       ],
        "status":  "confirmed",
        "created_at":  "2025-12-10 18:29:58",
        "updated_at":  "2025-11-14 18:35:10",
        "ceo_id":  2,
        "departure_time":  "2025-12-11T08:00:00"
    }
]